gldf_rs_python-0.3.3.dist-info/METADATA
gldf_rs_python-0.3.3.dist-info/WHEEL
gldf_rs_python/__init__.py
gldf_rs_python/gldf_rs_python.abi3.so
gldf_rs_python-0.3.3.dist-info/RECORD
