Metadata-Version: 2.4
Name: gldf-rs-python
Version: 0.3.3
Classifier: Development Status :: 4 - Beta
Classifier: Programming Language :: Rust
Classifier: Programming Language :: Python :: Implementation :: CPython
Classifier: Programming Language :: Python :: Implementation :: PyPy
Classifier: License :: OSI Approved :: MIT License
Classifier: Topic :: Scientific/Engineering
Summary: Python bindings for GLDF (General Lighting Data Format) parsing library
Keywords: gldf,lighting,photometry,eulumdat,ies
Home-Page: https://github.com/holg/gldf-rs
Author: Holger Trahe
License: MIT
Requires-Python: >=3.8
Project-URL: Homepage, https://gldf.icu
Project-URL: Repository, https://github.com/holg/gldf-rs
Project-URL: Documentation, https://docs.rs/gldf-rs/
